nnrl/__init__.py
nnrl/distributions/__init__.py
nnrl/distributions/diag_multivariate_normal.py
nnrl/distributions/logistic.py
nnrl/distributions/squashed_distribution.py
nnrl/distributions/transforms.py
nnrl/math.py
nnrl/nn/__init__.py
nnrl/nn/actor/__init__.py
nnrl/nn/actor/deterministic.py
nnrl/nn/actor/policy/__init__.py
nnrl/nn/actor/policy/deterministic.py
nnrl/nn/actor/policy/stochastic.py
nnrl/nn/actor/stochastic.py
nnrl/nn/critic/__init__.py
nnrl/nn/critic/action_value.py
nnrl/nn/critic/naf_value.py
nnrl/nn/critic/q_value.py
nnrl/nn/critic/v_value.py
nnrl/nn/distributions/__init__.py
nnrl/nn/distributions/abstract.py
nnrl/nn/distributions/categorical.py
nnrl/nn/distributions/flows/__init__.py
nnrl/nn/distributions/flows/abstract.py
nnrl/nn/distributions/flows/affine_constant.py
nnrl/nn/distributions/flows/coupling.py
nnrl/nn/distributions/flows/glow_1x1conv.py
nnrl/nn/distributions/flows/maf.py
nnrl/nn/distributions/flows/masks.py
nnrl/nn/distributions/flows/nonlinearities.py
nnrl/nn/distributions/flows/splines.py
nnrl/nn/distributions/flows/utils.py
nnrl/nn/distributions/normal.py
nnrl/nn/distributions/types.py
nnrl/nn/distributions/uniform.py
nnrl/nn/init.py
nnrl/nn/model/__init__.py
nnrl/nn/model/stochastic/__init__.py
nnrl/nn/model/stochastic/builders.py
nnrl/nn/model/stochastic/ensemble.py
nnrl/nn/model/stochastic/single.py
nnrl/nn/model/stochastic/svg.py
nnrl/nn/modules/__init__.py
nnrl/nn/modules/action_output.py
nnrl/nn/modules/activation.py
nnrl/nn/modules/dist_params.py
nnrl/nn/modules/fully_connected.py
nnrl/nn/modules/gaussian_noise.py
nnrl/nn/modules/lambd.py
nnrl/nn/modules/leaf_parameter.py
nnrl/nn/modules/linear.py
nnrl/nn/modules/tanh_squash.py
nnrl/nn/modules/tril_matrix.py
nnrl/nn/modules/utils.py
nnrl/nn/networks/__init__.py
nnrl/nn/networks/mlp.py
nnrl/nn/networks/resnet.py
nnrl/nn/networks/utils.py
nnrl/nn/utils.py
nnrl/optim/__init__.py
nnrl/optim/hessian_free.py
nnrl/optim/kfac.py
nnrl/optim/radam.py
nnrl/optim/utils.py
nnrl/types.py
nnrl-0.1.1.dist-info/LICENSE
nnrl-0.1.1.dist-info/WHEEL
nnrl-0.1.1.dist-info/METADATA
nnrl-0.1.1.dist-info/RECORD
