Metadata-Version: 2.1
Name: nnrl
Version: 0.1.1
Summary: Top-level package for NN RL.
Home-page: https://github.com/angelolovatto/nnrl
License: MIT
Author: Ângelo Gregório Lovatto
Author-email: angelolovatto@gmail.com
Requires-Python: >=3.7
Classifier: Development Status :: 2 - Pre-Alpha
Classifier: Intended Audience :: Developers
Classifier: License :: OSI Approved :: MIT License
Classifier: Natural Language :: English
Classifier: Programming Language :: Python :: 3
Classifier: Programming Language :: Python :: 3.10
Classifier: Programming Language :: Python :: 3.7
Classifier: Programming Language :: Python :: 3.8
Classifier: Programming Language :: Python :: 3.9
Requires-Dist: dataclasses-json (>=0.5.4,<0.6.0)
Requires-Dist: gym (>=0.23.0,<0.24.0)
Requires-Dist: torch (>=1.9.0,<2.0.0)
